nmb_eeg.py
nmb_eeg-1.0.dist-info/LICENSE
nmb_eeg-1.0.dist-info/METADATA
nmb_eeg-1.0.dist-info/WHEEL
nmb_eeg-1.0.dist-info/top_level.txt
nmb_eeg-1.0.dist-info/RECORD
