Metadata-Version: 2.1
Name: nmb-eeg
Version: 1.0
Summary: Power spectra of pure EEG from two temporarily paralysed subjects from Whitham et al 2007
Home-page: https://github.com/berndporr/nmb_eeg
Author: Bernd Porr
Author-email: bernd.porr@glasgow.ac.uk
License: GPL 3.0
Platform: UNKNOWN
Classifier: Intended Audience :: Developers
Classifier: Operating System :: OS Independent
Classifier: Programming Language :: Python :: 3
Requires-Dist: numpy
